test_tools_agilecode.py
test_tools_agilecode-0.3.0.dist-info/WHEEL
test_tools_agilecode-0.3.0.dist-info/METADATA
test_tools_agilecode-0.3.0.dist-info/RECORD
